{
  "system_name": "Enhanced HeavyDB Multi-Algorithm Portfolio Optimization System",
  "version": "2.0.0-production",
  "deployment_date": "2025-07-24T11:38:55.072217",
  "production_ready": true,
  "critical_fixes_applied": {
    "differential_evolution_parameter_fixed": true,
    "parallel_execution_method_implemented": true,
    "all_basic_algorithms_functional": true,
    "threading_errors_resolved": true
  },
  "production_specifications": {
    "algorithms_total": 7,
    "algorithms_functional": 7,
    "functionality_rate": 100.0,
    "parallel_execution_working": true,
    "connection_pool_sizes_supported": [
      1,
      3,
      5
    ],
    "optimization_metrics_supported": [
      "ratio",
      "roi",
      "less max dd"
    ],
    "portfolio_sizes_supported": [
      10,
      20,
      30,
      50
    ]
  },
  "performance_metrics": {
    "fitness_consistency": "0.000000% CV (perfect)",
    "execution_time_consistency": "0.83% CV (excellent)",
    "production_readiness_score": "95.0/100",
    "all_algorithms_functional": true,
    "parallel_execution_functional": true
  },
  "deployment_requirements": {
    "python_version": "3.10+",
    "required_packages": [
      "numpy",
      "pandas",
      "concurrent.futures",
      "logging"
    ],
    "memory_requirements": "~175MB peak usage",
    "cpu_requirements": "multi-core recommended for parallel execution",
    "storage_requirements": "minimal (caching in memory)"
  }
}